ark_client/__init__.py
ark_client/mapping.py
ark_client/mapping_inputs.py
cid_client/__init__.py
cid_client/mapping.py
cid_client/mapping_inputs.py
cid_client-0.2.3.dist-info/LICENSE.txt
cid_client-0.2.3.dist-info/METADATA
cid_client-0.2.3.dist-info/WHEEL
cid_client-0.2.3.dist-info/top_level.txt
cid_client-0.2.3.dist-info/RECORD
