Metadata-Version: 2.1
Name: cid-client
Version: 0.2.3
Summary: Client of CID Tool
Home-page: https://github.com/coherentdigital/cid-python
License: MIT
Platform: UNKNOWN
Requires-Python: >=3.7
License-File: LICENSE.txt
Requires-Dist: requests
